setup.py
bin/bitbucket
bitbucket/__init__.py
bitbucket/oauth1.py
py3bitbucket.egg-info/PKG-INFO
py3bitbucket.egg-info/SOURCES.txt
py3bitbucket.egg-info/dependency_links.txt
py3bitbucket.egg-info/requires.txt
py3bitbucket.egg-info/top_level.txt