Metadata-Version: 1.0
Name: py3bitbucket
Version: 0.0.3
Summary: bitbucket client
Home-page: https://github.com/c9s/py-bitbucket
Author: Yo-An lin
Author-email: yoanlin93@gmail.com
License: MIT
Platform: UNKNOWN
